synthetic_data_generator/__init__.py
synthetic_data_generator/generate_date.py
synthetic_data_generator/generate_number.py
synthetic_data_generator/generate_text.py
synthetic_data_generator_pkg-0.0.3.dist-info/LICENSE
synthetic_data_generator_pkg-0.0.3.dist-info/METADATA
synthetic_data_generator_pkg-0.0.3.dist-info/WHEEL
synthetic_data_generator_pkg-0.0.3.dist-info/top_level.txt
synthetic_data_generator_pkg-0.0.3.dist-info/RECORD
