Metadata-Version: 2.1
Name: synthetic-data-generator-pkg
Version: 0.0.3
Summary: Python package for generating synthetic data.
Home-page: https://github.com/Jeton-Digital/Synthetic-Data-Generator
Author: Efe Buyuk
Author-email: hello@jetondigital.com
License: UNKNOWN
Project-URL: Bug Tracker, https://github.com/Jeton-Digital/Synthetic-Data-Generator/issues
Platform: UNKNOWN
Classifier: Programming Language :: Python :: 3
Classifier: License :: OSI Approved :: MIT License
Classifier: Operating System :: OS Independent
Requires-Python: >=3.6
License-File: LICENSE
Requires-Dist: barnum
Requires-Dist: Faker
Requires-Dist: future
Requires-Dist: names
Requires-Dist: python-dateutil
Requires-Dist: six
Requires-Dist: text-unidecode
